midi_point_set/__init__.py
midi_point_set/__main__.py
midi_point_set/console.py
midi_point_set-0.1.0.dist-info/entry_points.txt
midi_point_set-0.1.0.dist-info/LICENSE
midi_point_set-0.1.0.dist-info/WHEEL
midi_point_set-0.1.0.dist-info/METADATA
midi_point_set-0.1.0.dist-info/RECORD
