Metadata-Version: 2.1
Name: midi-point-set
Version: 0.1.0
Summary: Convert MIDI files to point set representation.
License: MIT
Author: Leo
Author-email: leohdz.c0@gmail.com
Requires-Python: >=3.8,<4.0
Classifier: License :: OSI Approved :: MIT License
Classifier: Programming Language :: Python :: 3
Classifier: Programming Language :: Python :: 3.8
Classifier: Programming Language :: Python :: 3.9
Classifier: Programming Language :: Python :: 3.10
Requires-Dist: bokeh (>=3.1.0,<4.0.0)
Requires-Dist: matplotlib (>=3.7.1,<4.0.0)
Requires-Dist: pretty_midi (>=0.2.10,<0.3.0)
